{"frames": [

{
	"filename": "ad.png",
	"frame": {"x":413,"y":427,"w":32,"h":22},
	"rotated": false,
	"trimmed": false,
	"spriteSourceSize": {"x":0,"y":0,"w":32,"h":22},
	"sourceSize": {"w":32,"h":22}
},
{
	"filename": "ae.png",
	"frame": {"x":403,"y":391,"w":32,"h":22},
	"rotated": true,
	"trimmed": false,
	"spriteSourceSize": {"x":0,"y":0,"w":32,"h":22},
	"sourceSize": {"w":32,"h":22}
},
{
	"filename": "af.png",
	"frame": {"x":403,"y":365,"w":32,"h":22},
	"rotated": false,
	"trimmed": false,
	"spriteSourceSize": {"x":0,"y":0,"w":32,"h":22},
	"sourceSize": {"w":32,"h":22}
},
{
	"filename": "ag.png",
	"frame": {"x":411,"y":479,"w":32,"h":22},
	"rotated": false,
	"trimmed": false,
	"spriteSourceSize": {"x":0,"y":0,"w":32,"h":22},
	"sourceSize": {"w":32,"h":22}
},
{
	"filename": "ai.png",
	"frame": {"x":387,"y":443,"w":32,"h":22},
	"rotated": true,
	"trimmed": false,
	"spriteSourceSize": {"x":0,"y":0,"w":32,"h":22},
	"sourceSize": {"w":32,"h":22}
},
{
	"filename": "al.png",
	"frame": {"x":377,"y":407,"w":32,"h":22},
	"rotated": true,
	"trimmed": false,
	"spriteSourceSize": {"x":0,"y":0,"w":32,"h":22},
	"sourceSize": {"w":32,"h":22}
},
{
	"filename": "am.png",
	"frame": {"x":375,"y":485,"w":32,"h":22},
	"rotated": false,
	"trimmed": false,
	"spriteSourceSize": {"x":0,"y":0,"w":32,"h":22},
	"sourceSize": {"w":32,"h":22}
},
{
	"filename": "an.png",
	"frame": {"x":361,"y":449,"w":32,"h":22},
	"rotated": true,
	"trimmed": false,
	"spriteSourceSize": {"x":0,"y":0,"w":32,"h":22},
	"sourceSize": {"w":32,"h":22}
},
{
	"filename": "ao.png",
	"frame": {"x":367,"y":381,"w":32,"h":22},
	"rotated": false,
	"trimmed": false,
	"spriteSourceSize": {"x":0,"y":0,"w":32,"h":22},
	"sourceSize": {"w":32,"h":22}
},
{
	"filename": "ar.png",
	"frame": {"x":367,"y":355,"w":32,"h":22},
	"rotated": false,
	"trimmed": false,
	"spriteSourceSize": {"x":0,"y":0,"w":32,"h":22},
	"sourceSize": {"w":32,"h":22}
},
{
	"filename": "as.png",
	"frame": {"x":351,"y":413,"w":32,"h":22},
	"rotated": true,
	"trimmed": false,
	"spriteSourceSize": {"x":0,"y":0,"w":32,"h":22},
	"sourceSize": {"w":32,"h":22}
},
{
	"filename": "at.png",
	"frame": {"x":339,"y":485,"w":32,"h":22},
	"rotated": false,
	"trimmed": false,
	"spriteSourceSize": {"x":0,"y":0,"w":32,"h":22},
	"sourceSize": {"w":32,"h":22}
},
{
	"filename": "au.png",
	"frame": {"x":335,"y":449,"w":32,"h":22},
	"rotated": true,
	"trimmed": false,
	"spriteSourceSize": {"x":0,"y":0,"w":32,"h":22},
	"sourceSize": {"w":32,"h":22}
},
{
	"filename": "aw.png",
	"frame": {"x":341,"y":377,"w":32,"h":22},
	"rotated": true,
	"trimmed": false,
	"spriteSourceSize": {"x":0,"y":0,"w":32,"h":22},
	"sourceSize": {"w":32,"h":22}
},
{
	"filename": "ax.png",
	"frame": {"x":325,"y":413,"w":32,"h":22},
	"rotated": true,
	"trimmed": false,
	"spriteSourceSize": {"x":0,"y":0,"w":32,"h":22},
	"sourceSize": {"w":32,"h":22}
},
{
	"filename": "az.png",
	"frame": {"x":309,"y":449,"w":32,"h":22},
	"rotated": true,
	"trimmed": false,
	"spriteSourceSize": {"x":0,"y":0,"w":32,"h":22},
	"sourceSize": {"w":32,"h":22}
},
{
	"filename": "ba.png",
	"frame": {"x":325,"y":341,"w":32,"h":22},
	"rotated": true,
	"trimmed": false,
	"spriteSourceSize": {"x":0,"y":0,"w":32,"h":22},
	"sourceSize": {"w":32,"h":22}
},
{
	"filename": "bb.png",
	"frame": {"x":315,"y":377,"w":32,"h":22},
	"rotated": true,
	"trimmed": false,
	"spriteSourceSize": {"x":0,"y":0,"w":32,"h":22},
	"sourceSize": {"w":32,"h":22}
},
{
	"filename": "bd.png",
	"frame": {"x":299,"y":413,"w":32,"h":22},
	"rotated": true,
	"trimmed": false,
	"spriteSourceSize": {"x":0,"y":0,"w":32,"h":22},
	"sourceSize": {"w":32,"h":22}
},
{
	"filename": "be.png",
	"frame": {"x":303,"y":485,"w":32,"h":22},
	"rotated": false,
	"trimmed": false,
	"spriteSourceSize": {"x":0,"y":0,"w":32,"h":22},
	"sourceSize": {"w":32,"h":22}
},
{
	"filename": "bf.png",
	"frame": {"x":283,"y":449,"w":32,"h":22},
	"rotated": true,
	"trimmed": false,
	"spriteSourceSize": {"x":0,"y":0,"w":32,"h":22},
	"sourceSize": {"w":32,"h":22}
},
{
	"filename": "bg.png",
	"frame": {"x":299,"y":341,"w":32,"h":22},
	"rotated": true,
	"trimmed": false,
	"spriteSourceSize": {"x":0,"y":0,"w":32,"h":22},
	"sourceSize": {"w":32,"h":22}
},
{
	"filename": "bh.png",
	"frame": {"x":289,"y":377,"w":32,"h":22},
	"rotated": true,
	"trimmed": false,
	"spriteSourceSize": {"x":0,"y":0,"w":32,"h":22},
	"sourceSize": {"w":32,"h":22}
},
{
	"filename": "bi.png",
	"frame": {"x":273,"y":413,"w":32,"h":22},
	"rotated": true,
	"trimmed": false,
	"spriteSourceSize": {"x":0,"y":0,"w":32,"h":22},
	"sourceSize": {"w":32,"h":22}
},
{
	"filename": "bj.png",
	"frame": {"x":267,"y":485,"w":32,"h":22},
	"rotated": false,
	"trimmed": false,
	"spriteSourceSize": {"x":0,"y":0,"w":32,"h":22},
	"sourceSize": {"w":32,"h":22}
},
{
	"filename": "bm.png",
	"frame": {"x":257,"y":449,"w":32,"h":22},
	"rotated": true,
	"trimmed": false,
	"spriteSourceSize": {"x":0,"y":0,"w":32,"h":22},
	"sourceSize": {"w":32,"h":22}
},
{
	"filename": "bn.png",
	"frame": {"x":273,"y":341,"w":32,"h":22},
	"rotated": true,
	"trimmed": false,
	"spriteSourceSize": {"x":0,"y":0,"w":32,"h":22},
	"sourceSize": {"w":32,"h":22}
},
{
	"filename": "bo.png",
	"frame": {"x":263,"y":377,"w":32,"h":22},
	"rotated": true,
	"trimmed": false,
	"spriteSourceSize": {"x":0,"y":0,"w":32,"h":22},
	"sourceSize": {"w":32,"h":22}
},
{
	"filename": "br.png",
	"frame": {"x":247,"y":413,"w":32,"h":22},
	"rotated": true,
	"trimmed": false,
	"spriteSourceSize": {"x":0,"y":0,"w":32,"h":22},
	"sourceSize": {"w":32,"h":22}
},
{
	"filename": "bs.png",
	"frame": {"x":231,"y":485,"w":32,"h":22},
	"rotated": false,
	"trimmed": false,
	"spriteSourceSize": {"x":0,"y":0,"w":32,"h":22},
	"sourceSize": {"w":32,"h":22}
},
{
	"filename": "bt.png",
	"frame": {"x":231,"y":449,"w":32,"h":22},
	"rotated": true,
	"trimmed": false,
	"spriteSourceSize": {"x":0,"y":0,"w":32,"h":22},
	"sourceSize": {"w":32,"h":22}
},
{
	"filename": "bv.png",
	"frame": {"x":247,"y":341,"w":32,"h":22},
	"rotated": true,
	"trimmed": false,
	"spriteSourceSize": {"x":0,"y":0,"w":32,"h":22},
	"sourceSize": {"w":32,"h":22}
},
{
	"filename": "bw.png",
	"frame": {"x":237,"y":377,"w":32,"h":22},
	"rotated": true,
	"trimmed": false,
	"spriteSourceSize": {"x":0,"y":0,"w":32,"h":22},
	"sourceSize": {"w":32,"h":22}
},
{
	"filename": "by.png",
	"frame": {"x":221,"y":413,"w":32,"h":22},
	"rotated": true,
	"trimmed": false,
	"spriteSourceSize": {"x":0,"y":0,"w":32,"h":22},
	"sourceSize": {"w":32,"h":22}
},
{
	"filename": "bz.png",
	"frame": {"x":205,"y":459,"w":32,"h":22},
	"rotated": true,
	"trimmed": false,
	"spriteSourceSize": {"x":0,"y":0,"w":32,"h":22},
	"sourceSize": {"w":32,"h":22}
},
{
	"filename": "ca.png",
	"frame": {"x":221,"y":341,"w":32,"h":22},
	"rotated": true,
	"trimmed": false,
	"spriteSourceSize": {"x":0,"y":0,"w":32,"h":22},
	"sourceSize": {"w":32,"h":22}
},
{
	"filename": "cc.png",
	"frame": {"x":211,"y":377,"w":32,"h":22},
	"rotated": true,
	"trimmed": false,
	"spriteSourceSize": {"x":0,"y":0,"w":32,"h":22},
	"sourceSize": {"w":32,"h":22}
},
{
	"filename": "cd.png",
	"frame": {"x":195,"y":423,"w":32,"h":22},
	"rotated": true,
	"trimmed": false,
	"spriteSourceSize": {"x":0,"y":0,"w":32,"h":22},
	"sourceSize": {"w":32,"h":22}
},
{
	"filename": "cf.png",
	"frame": {"x":185,"y":387,"w":32,"h":22},
	"rotated": true,
	"trimmed": false,
	"spriteSourceSize": {"x":0,"y":0,"w":32,"h":22},
	"sourceSize": {"w":32,"h":22}
},
{
	"filename": "cg.png",
	"frame": {"x":169,"y":479,"w":32,"h":22},
	"rotated": false,
	"trimmed": false,
	"spriteSourceSize": {"x":0,"y":0,"w":32,"h":22},
	"sourceSize": {"w":32,"h":22}
},
{
	"filename": "ch.png",
	"frame": {"x":429,"y":391,"w":22,"h":22},
	"rotated": false,
	"trimmed": false,
	"spriteSourceSize": {"x":0,"y":0,"w":22,"h":22},
	"sourceSize": {"w":22,"h":22}
},
{
	"filename": "ci.png",
	"frame": {"x":169,"y":443,"w":32,"h":22},
	"rotated": true,
	"trimmed": false,
	"spriteSourceSize": {"x":0,"y":0,"w":32,"h":22},
	"sourceSize": {"w":32,"h":22}
},
{
	"filename": "ck.png",
	"frame": {"x":159,"y":407,"w":32,"h":22},
	"rotated": true,
	"trimmed": false,
	"spriteSourceSize": {"x":0,"y":0,"w":32,"h":22},
	"sourceSize": {"w":32,"h":22}
},
{
	"filename": "cl.png",
	"frame": {"x":143,"y":453,"w":32,"h":22},
	"rotated": true,
	"trimmed": false,
	"spriteSourceSize": {"x":0,"y":0,"w":32,"h":22},
	"sourceSize": {"w":32,"h":22}
},
{
	"filename": "cm.png",
	"frame": {"x":133,"y":417,"w":32,"h":22},
	"rotated": true,
	"trimmed": false,
	"spriteSourceSize": {"x":0,"y":0,"w":32,"h":22},
	"sourceSize": {"w":32,"h":22}
},
{
	"filename": "cn.png",
	"frame": {"x":117,"y":463,"w":32,"h":22},
	"rotated": true,
	"trimmed": false,
	"spriteSourceSize": {"x":0,"y":0,"w":32,"h":22},
	"sourceSize": {"w":32,"h":22}
},
{
	"filename": "co.png",
	"frame": {"x":107,"y":427,"w":32,"h":22},
	"rotated": true,
	"trimmed": false,
	"spriteSourceSize": {"x":0,"y":0,"w":32,"h":22},
	"sourceSize": {"w":32,"h":22}
},
{
	"filename": "cr.png",
	"frame": {"x":81,"y":483,"w":32,"h":22},
	"rotated": false,
	"trimmed": false,
	"spriteSourceSize": {"x":0,"y":0,"w":32,"h":22},
	"sourceSize": {"w":32,"h":22}
},
{
	"filename": "cs.png",
	"frame": {"x":81,"y":447,"w":32,"h":22},
	"rotated": true,
	"trimmed": false,
	"spriteSourceSize": {"x":0,"y":0,"w":32,"h":22},
	"sourceSize": {"w":32,"h":22}
},
{
	"filename": "cu.png",
	"frame": {"x":55,"y":457,"w":32,"h":22},
	"rotated": true,
	"trimmed": false,
	"spriteSourceSize": {"x":0,"y":0,"w":32,"h":22},
	"sourceSize": {"w":32,"h":22}
},
{
	"filename": "cv.png",
	"frame": {"x":29,"y":473,"w":32,"h":22},
	"rotated": true,
	"trimmed": false,
	"spriteSourceSize": {"x":0,"y":0,"w":32,"h":22},
	"sourceSize": {"w":32,"h":22}
},
{
	"filename": "cx.png",
	"frame": {"x":3,"y":473,"w":32,"h":22},
	"rotated": true,
	"trimmed": false,
	"spriteSourceSize": {"x":0,"y":0,"w":32,"h":22},
	"sourceSize": {"w":32,"h":22}
},
{
	"filename": "cy.png",
	"frame": {"x":3,"y":447,"w":32,"h":22},
	"rotated": false,
	"trimmed": false,
	"spriteSourceSize": {"x":0,"y":0,"w":32,"h":22},
	"sourceSize": {"w":32,"h":22}
},
{
	"filename": "cz.png",
	"frame": {"x":39,"y":421,"w":32,"h":22},
	"rotated": true,
	"trimmed": false,
	"spriteSourceSize": {"x":0,"y":0,"w":32,"h":22},
	"sourceSize": {"w":32,"h":22}
},
{
	"filename": "de.png",
	"frame": {"x":3,"y":421,"w":32,"h":22},
	"rotated": false,
	"trimmed": false,
	"spriteSourceSize": {"x":0,"y":0,"w":32,"h":22},
	"sourceSize": {"w":32,"h":22}
},
{
	"filename": "dj.png",
	"frame": {"x":65,"y":411,"w":32,"h":22},
	"rotated": true,
	"trimmed": false,
	"spriteSourceSize": {"x":0,"y":0,"w":32,"h":22},
	"sourceSize": {"w":32,"h":22}
},
{
	"filename": "dk.png",
	"frame": {"x":91,"y":391,"w":32,"h":22},
	"rotated": true,
	"trimmed": false,
	"spriteSourceSize": {"x":0,"y":0,"w":32,"h":22},
	"sourceSize": {"w":32,"h":22}
},
{
	"filename": "dm.png",
	"frame": {"x":117,"y":381,"w":32,"h":22},
	"rotated": true,
	"trimmed": false,
	"spriteSourceSize": {"x":0,"y":0,"w":32,"h":22},
	"sourceSize": {"w":32,"h":22}
},
{
	"filename": "do.png",
	"frame": {"x":143,"y":371,"w":32,"h":22},
	"rotated": true,
	"trimmed": false,
	"spriteSourceSize": {"x":0,"y":0,"w":32,"h":22},
	"sourceSize": {"w":32,"h":22}
},
{
	"filename": "dz.png",
	"frame": {"x":169,"y":351,"w":32,"h":22},
	"rotated": true,
	"trimmed": false,
	"spriteSourceSize": {"x":0,"y":0,"w":32,"h":22},
	"sourceSize": {"w":32,"h":22}
},
{
	"filename": "ec.png",
	"frame": {"x":195,"y":341,"w":32,"h":22},
	"rotated": true,
	"trimmed": false,
	"spriteSourceSize": {"x":0,"y":0,"w":32,"h":22},
	"sourceSize": {"w":32,"h":22}
},
{
	"filename": "ee.png",
	"frame": {"x":411,"y":339,"w":32,"h":22},
	"rotated": false,
	"trimmed": false,
	"spriteSourceSize": {"x":0,"y":0,"w":32,"h":22},
	"sourceSize": {"w":32,"h":22}
},
{
	"filename": "eg.png",
	"frame": {"x":375,"y":329,"w":32,"h":22},
	"rotated": false,
	"trimmed": false,
	"spriteSourceSize": {"x":0,"y":0,"w":32,"h":22},
	"sourceSize": {"w":32,"h":22}
},
{
	"filename": "eh.png",
	"frame": {"x":339,"y":315,"w":32,"h":22},
	"rotated": false,
	"trimmed": false,
	"spriteSourceSize": {"x":0,"y":0,"w":32,"h":22},
	"sourceSize": {"w":32,"h":22}
},
{
	"filename": "er.png",
	"frame": {"x":303,"y":315,"w":32,"h":22},
	"rotated": false,
	"trimmed": false,
	"spriteSourceSize": {"x":0,"y":0,"w":32,"h":22},
	"sourceSize": {"w":32,"h":22}
},
{
	"filename": "es.png",
	"frame": {"x":267,"y":315,"w":32,"h":22},
	"rotated": false,
	"trimmed": false,
	"spriteSourceSize": {"x":0,"y":0,"w":32,"h":22},
	"sourceSize": {"w":32,"h":22}
},
{
	"filename": "et.png",
	"frame": {"x":231,"y":315,"w":32,"h":22},
	"rotated": false,
	"trimmed": false,
	"spriteSourceSize": {"x":0,"y":0,"w":32,"h":22},
	"sourceSize": {"w":32,"h":22}
},
{
	"filename": "fi.png",
	"frame": {"x":195,"y":315,"w":32,"h":22},
	"rotated": false,
	"trimmed": false,
	"spriteSourceSize": {"x":0,"y":0,"w":32,"h":22},
	"sourceSize": {"w":32,"h":22}
},
{
	"filename": "fj.png",
	"frame": {"x":3,"y":395,"w":32,"h":22},
	"rotated": false,
	"trimmed": false,
	"spriteSourceSize": {"x":0,"y":0,"w":32,"h":22},
	"sourceSize": {"w":32,"h":22}
},
{
	"filename": "fk.png",
	"frame": {"x":39,"y":385,"w":32,"h":22},
	"rotated": true,
	"trimmed": false,
	"spriteSourceSize": {"x":0,"y":0,"w":32,"h":22},
	"sourceSize": {"w":32,"h":22}
},
{
	"filename": "fm.png",
	"frame": {"x":65,"y":375,"w":32,"h":22},
	"rotated": true,
	"trimmed": false,
	"spriteSourceSize": {"x":0,"y":0,"w":32,"h":22},
	"sourceSize": {"w":32,"h":22}
},
{
	"filename": "fo.png",
	"frame": {"x":91,"y":355,"w":32,"h":22},
	"rotated": true,
	"trimmed": false,
	"spriteSourceSize": {"x":0,"y":0,"w":32,"h":22},
	"sourceSize": {"w":32,"h":22}
},
{
	"filename": "fr.png",
	"frame": {"x":117,"y":345,"w":32,"h":22},
	"rotated": true,
	"trimmed": false,
	"spriteSourceSize": {"x":0,"y":0,"w":32,"h":22},
	"sourceSize": {"w":32,"h":22}
},
{
	"filename": "ga.png",
	"frame": {"x":143,"y":335,"w":32,"h":22},
	"rotated": true,
	"trimmed": false,
	"spriteSourceSize": {"x":0,"y":0,"w":32,"h":22},
	"sourceSize": {"w":32,"h":22}
},
{
	"filename": "gb.png",
	"frame": {"x":169,"y":315,"w":32,"h":22},
	"rotated": true,
	"trimmed": false,
	"spriteSourceSize": {"x":0,"y":0,"w":32,"h":22},
	"sourceSize": {"w":32,"h":22}
},
{
	"filename": "gd.png",
	"frame": {"x":421,"y":313,"w":32,"h":22},
	"rotated": false,
	"trimmed": false,
	"spriteSourceSize": {"x":0,"y":0,"w":32,"h":22},
	"sourceSize": {"w":32,"h":22}
},
{
	"filename": "ge.png",
	"frame": {"x":385,"y":303,"w":32,"h":22},
	"rotated": false,
	"trimmed": false,
	"spriteSourceSize": {"x":0,"y":0,"w":32,"h":22},
	"sourceSize": {"w":32,"h":22}
},
{
	"filename": "gf.png",
	"frame": {"x":117,"y":345,"w":32,"h":22},
	"rotated": true,
	"trimmed": false,
	"spriteSourceSize": {"x":0,"y":0,"w":32,"h":22},
	"sourceSize": {"w":32,"h":22}
},
{
	"filename": "gh.png",
	"frame": {"x":349,"y":289,"w":32,"h":22},
	"rotated": false,
	"trimmed": false,
	"spriteSourceSize": {"x":0,"y":0,"w":32,"h":22},
	"sourceSize": {"w":32,"h":22}
},
{
	"filename": "gi.png",
	"frame": {"x":313,"y":289,"w":32,"h":22},
	"rotated": false,
	"trimmed": false,
	"spriteSourceSize": {"x":0,"y":0,"w":32,"h":22},
	"sourceSize": {"w":32,"h":22}
},
{
	"filename": "gl.png",
	"frame": {"x":277,"y":289,"w":32,"h":22},
	"rotated": false,
	"trimmed": false,
	"spriteSourceSize": {"x":0,"y":0,"w":32,"h":22},
	"sourceSize": {"w":32,"h":22}
},
{
	"filename": "gm.png",
	"frame": {"x":241,"y":289,"w":32,"h":22},
	"rotated": false,
	"trimmed": false,
	"spriteSourceSize": {"x":0,"y":0,"w":32,"h":22},
	"sourceSize": {"w":32,"h":22}
},
{
	"filename": "gn.png",
	"frame": {"x":205,"y":289,"w":32,"h":22},
	"rotated": false,
	"trimmed": false,
	"spriteSourceSize": {"x":0,"y":0,"w":32,"h":22},
	"sourceSize": {"w":32,"h":22}
},
{
	"filename": "gp.png",
	"frame": {"x":3,"y":369,"w":32,"h":22},
	"rotated": false,
	"trimmed": false,
	"spriteSourceSize": {"x":0,"y":0,"w":32,"h":22},
	"sourceSize": {"w":32,"h":22}
},
{
	"filename": "gq.png",
	"frame": {"x":39,"y":349,"w":32,"h":22},
	"rotated": true,
	"trimmed": false,
	"spriteSourceSize": {"x":0,"y":0,"w":32,"h":22},
	"sourceSize": {"w":32,"h":22}
},
{
	"filename": "gr.png",
	"frame": {"x":65,"y":339,"w":32,"h":22},
	"rotated": true,
	"trimmed": false,
	"spriteSourceSize": {"x":0,"y":0,"w":32,"h":22},
	"sourceSize": {"w":32,"h":22}
},
{
	"filename": "gs.png",
	"frame": {"x":91,"y":319,"w":32,"h":22},
	"rotated": true,
	"trimmed": false,
	"spriteSourceSize": {"x":0,"y":0,"w":32,"h":22},
	"sourceSize": {"w":32,"h":22}
},
{
	"filename": "gt.png",
	"frame": {"x":117,"y":309,"w":32,"h":22},
	"rotated": true,
	"trimmed": false,
	"spriteSourceSize": {"x":0,"y":0,"w":32,"h":22},
	"sourceSize": {"w":32,"h":22}
},
{
	"filename": "gu.png",
	"frame": {"x":143,"y":299,"w":32,"h":22},
	"rotated": true,
	"trimmed": false,
	"spriteSourceSize": {"x":0,"y":0,"w":32,"h":22},
	"sourceSize": {"w":32,"h":22}
},
{
	"filename": "gw.png",
	"frame": {"x":169,"y":289,"w":32,"h":22},
	"rotated": false,
	"trimmed": false,
	"spriteSourceSize": {"x":0,"y":0,"w":32,"h":22},
	"sourceSize": {"w":32,"h":22}
},
{
	"filename": "gy.png",
	"frame": {"x":421,"y":287,"w":32,"h":22},
	"rotated": false,
	"trimmed": false,
	"spriteSourceSize": {"x":0,"y":0,"w":32,"h":22},
	"sourceSize": {"w":32,"h":22}
},
{
	"filename": "hk.png",
	"frame": {"x":385,"y":277,"w":32,"h":22},
	"rotated": false,
	"trimmed": false,
	"spriteSourceSize": {"x":0,"y":0,"w":32,"h":22},
	"sourceSize": {"w":32,"h":22}
},
{
	"filename": "hm.png",
	"frame": {"x":335,"y":449,"w":32,"h":22},
	"rotated": true,
	"trimmed": false,
	"spriteSourceSize": {"x":0,"y":0,"w":32,"h":22},
	"sourceSize": {"w":32,"h":22}
},
{
	"filename": "hn.png",
	"frame": {"x":349,"y":263,"w":32,"h":22},
	"rotated": false,
	"trimmed": false,
	"spriteSourceSize": {"x":0,"y":0,"w":32,"h":22},
	"sourceSize": {"w":32,"h":22}
},
{
	"filename": "hr.png",
	"frame": {"x":313,"y":263,"w":32,"h":22},
	"rotated": false,
	"trimmed": false,
	"spriteSourceSize": {"x":0,"y":0,"w":32,"h":22},
	"sourceSize": {"w":32,"h":22}
},
{
	"filename": "ht.png",
	"frame": {"x":277,"y":263,"w":32,"h":22},
	"rotated": false,
	"trimmed": false,
	"spriteSourceSize": {"x":0,"y":0,"w":32,"h":22},
	"sourceSize": {"w":32,"h":22}
},
{
	"filename": "hu.png",
	"frame": {"x":241,"y":263,"w":32,"h":22},
	"rotated": false,
	"trimmed": false,
	"spriteSourceSize": {"x":0,"y":0,"w":32,"h":22},
	"sourceSize": {"w":32,"h":22}
},
{
	"filename": "id.png",
	"frame": {"x":205,"y":263,"w":32,"h":22},
	"rotated": false,
	"trimmed": false,
	"spriteSourceSize": {"x":0,"y":0,"w":32,"h":22},
	"sourceSize": {"w":32,"h":22}
},
{
	"filename": "ie.png",
	"frame": {"x":169,"y":263,"w":32,"h":22},
	"rotated": false,
	"trimmed": false,
	"spriteSourceSize": {"x":0,"y":0,"w":32,"h":22},
	"sourceSize": {"w":32,"h":22}
},
{
	"filename": "il.png",
	"frame": {"x":3,"y":343,"w":32,"h":22},
	"rotated": false,
	"trimmed": false,
	"spriteSourceSize": {"x":0,"y":0,"w":32,"h":22},
	"sourceSize": {"w":32,"h":22}
},
{
	"filename": "in.png",
	"frame": {"x":3,"y":317,"w":32,"h":22},
	"rotated": false,
	"trimmed": false,
	"spriteSourceSize": {"x":0,"y":0,"w":32,"h":22},
	"sourceSize": {"w":32,"h":22}
},
{
	"filename": "io.png",
	"frame": {"x":39,"y":313,"w":32,"h":22},
	"rotated": true,
	"trimmed": false,
	"spriteSourceSize": {"x":0,"y":0,"w":32,"h":22},
	"sourceSize": {"w":32,"h":22}
},
{
	"filename": "iq.png",
	"frame": {"x":65,"y":303,"w":32,"h":22},
	"rotated": true,
	"trimmed": false,
	"spriteSourceSize": {"x":0,"y":0,"w":32,"h":22},
	"sourceSize": {"w":32,"h":22}
},
{
	"filename": "ir.png",
	"frame": {"x":91,"y":283,"w":32,"h":22},
	"rotated": true,
	"trimmed": false,
	"spriteSourceSize": {"x":0,"y":0,"w":32,"h":22},
	"sourceSize": {"w":32,"h":22}
},
{
	"filename": "is.png",
	"frame": {"x":117,"y":273,"w":32,"h":22},
	"rotated": true,
	"trimmed": false,
	"spriteSourceSize": {"x":0,"y":0,"w":32,"h":22},
	"sourceSize": {"w":32,"h":22}
},
{
	"filename": "it.png",
	"frame": {"x":143,"y":263,"w":32,"h":22},
	"rotated": true,
	"trimmed": false,
	"spriteSourceSize": {"x":0,"y":0,"w":32,"h":22},
	"sourceSize": {"w":32,"h":22}
},
{
	"filename": "jm.png",
	"frame": {"x":431,"y":251,"w":32,"h":22},
	"rotated": true,
	"trimmed": false,
	"spriteSourceSize": {"x":0,"y":0,"w":32,"h":22},
	"sourceSize": {"w":32,"h":22}
},
{
	"filename": "jo.png",
	"frame": {"x":395,"y":251,"w":32,"h":22},
	"rotated": false,
	"trimmed": false,
	"spriteSourceSize": {"x":0,"y":0,"w":32,"h":22},
	"sourceSize": {"w":32,"h":22}
},
{
	"filename": "jp.png",
	"frame": {"x":359,"y":237,"w":32,"h":22},
	"rotated": false,
	"trimmed": false,
	"spriteSourceSize": {"x":0,"y":0,"w":32,"h":22},
	"sourceSize": {"w":32,"h":22}
},
{
	"filename": "ke.png",
	"frame": {"x":323,"y":237,"w":32,"h":22},
	"rotated": false,
	"trimmed": false,
	"spriteSourceSize": {"x":0,"y":0,"w":32,"h":22},
	"sourceSize": {"w":32,"h":22}
},
{
	"filename": "kg.png",
	"frame": {"x":287,"y":237,"w":32,"h":22},
	"rotated": false,
	"trimmed": false,
	"spriteSourceSize": {"x":0,"y":0,"w":32,"h":22},
	"sourceSize": {"w":32,"h":22}
},
{
	"filename": "kh.png",
	"frame": {"x":251,"y":237,"w":32,"h":22},
	"rotated": false,
	"trimmed": false,
	"spriteSourceSize": {"x":0,"y":0,"w":32,"h":22},
	"sourceSize": {"w":32,"h":22}
},
{
	"filename": "ki.png",
	"frame": {"x":215,"y":237,"w":32,"h":22},
	"rotated": false,
	"trimmed": false,
	"spriteSourceSize": {"x":0,"y":0,"w":32,"h":22},
	"sourceSize": {"w":32,"h":22}
},
{
	"filename": "km.png",
	"frame": {"x":179,"y":237,"w":32,"h":22},
	"rotated": false,
	"trimmed": false,
	"spriteSourceSize": {"x":0,"y":0,"w":32,"h":22},
	"sourceSize": {"w":32,"h":22}
},
{
	"filename": "kn.png",
	"frame": {"x":143,"y":237,"w":32,"h":22},
	"rotated": false,
	"trimmed": false,
	"spriteSourceSize": {"x":0,"y":0,"w":32,"h":22},
	"sourceSize": {"w":32,"h":22}
},
{
	"filename": "kp.png",
	"frame": {"x":3,"y":291,"w":32,"h":22},
	"rotated": false,
	"trimmed": false,
	"spriteSourceSize": {"x":0,"y":0,"w":32,"h":22},
	"sourceSize": {"w":32,"h":22}
},
{
	"filename": "kr.png",
	"frame": {"x":39,"y":277,"w":32,"h":22},
	"rotated": true,
	"trimmed": false,
	"spriteSourceSize": {"x":0,"y":0,"w":32,"h":22},
	"sourceSize": {"w":32,"h":22}
},
{
	"filename": "kw.png",
	"frame": {"x":65,"y":267,"w":32,"h":22},
	"rotated": true,
	"trimmed": false,
	"spriteSourceSize": {"x":0,"y":0,"w":32,"h":22},
	"sourceSize": {"w":32,"h":22}
},
{
	"filename": "ky.png",
	"frame": {"x":91,"y":247,"w":32,"h":22},
	"rotated": true,
	"trimmed": false,
	"spriteSourceSize": {"x":0,"y":0,"w":32,"h":22},
	"sourceSize": {"w":32,"h":22}
},
{
	"filename": "kz.png",
	"frame": {"x":117,"y":237,"w":32,"h":22},
	"rotated": true,
	"trimmed": false,
	"spriteSourceSize": {"x":0,"y":0,"w":32,"h":22},
	"sourceSize": {"w":32,"h":22}
},
{
	"filename": "la.png",
	"frame": {"x":405,"y":225,"w":32,"h":22},
	"rotated": false,
	"trimmed": false,
	"spriteSourceSize": {"x":0,"y":0,"w":32,"h":22},
	"sourceSize": {"w":32,"h":22}
},
{
	"filename": "lb.png",
	"frame": {"x":369,"y":211,"w":32,"h":22},
	"rotated": false,
	"trimmed": false,
	"spriteSourceSize": {"x":0,"y":0,"w":32,"h":22},
	"sourceSize": {"w":32,"h":22}
},
{
	"filename": "lc.png",
	"frame": {"x":333,"y":211,"w":32,"h":22},
	"rotated": false,
	"trimmed": false,
	"spriteSourceSize": {"x":0,"y":0,"w":32,"h":22},
	"sourceSize": {"w":32,"h":22}
},
{
	"filename": "li.png",
	"frame": {"x":297,"y":211,"w":32,"h":22},
	"rotated": false,
	"trimmed": false,
	"spriteSourceSize": {"x":0,"y":0,"w":32,"h":22},
	"sourceSize": {"w":32,"h":22}
},
{
	"filename": "lk.png",
	"frame": {"x":261,"y":211,"w":32,"h":22},
	"rotated": false,
	"trimmed": false,
	"spriteSourceSize": {"x":0,"y":0,"w":32,"h":22},
	"sourceSize": {"w":32,"h":22}
},
{
	"filename": "lr.png",
	"frame": {"x":225,"y":211,"w":32,"h":22},
	"rotated": false,
	"trimmed": false,
	"spriteSourceSize": {"x":0,"y":0,"w":32,"h":22},
	"sourceSize": {"w":32,"h":22}
},
{
	"filename": "ls.png",
	"frame": {"x":189,"y":211,"w":32,"h":22},
	"rotated": false,
	"trimmed": false,
	"spriteSourceSize": {"x":0,"y":0,"w":32,"h":22},
	"sourceSize": {"w":32,"h":22}
},
{
	"filename": "lt.png",
	"frame": {"x":153,"y":211,"w":32,"h":22},
	"rotated": false,
	"trimmed": false,
	"spriteSourceSize": {"x":0,"y":0,"w":32,"h":22},
	"sourceSize": {"w":32,"h":22}
},
{
	"filename": "lu.png",
	"frame": {"x":117,"y":211,"w":32,"h":22},
	"rotated": false,
	"trimmed": false,
	"spriteSourceSize": {"x":0,"y":0,"w":32,"h":22},
	"sourceSize": {"w":32,"h":22}
},
{
	"filename": "lv.png",
	"frame": {"x":3,"y":265,"w":32,"h":22},
	"rotated": false,
	"trimmed": false,
	"spriteSourceSize": {"x":0,"y":0,"w":32,"h":22},
	"sourceSize": {"w":32,"h":22}
},
{
	"filename": "ly.png",
	"frame": {"x":39,"y":241,"w":32,"h":22},
	"rotated": true,
	"trimmed": false,
	"spriteSourceSize": {"x":0,"y":0,"w":32,"h":22},
	"sourceSize": {"w":32,"h":22}
},
{
	"filename": "ma.png",
	"frame": {"x":65,"y":231,"w":32,"h":22},
	"rotated": true,
	"trimmed": false,
	"spriteSourceSize": {"x":0,"y":0,"w":32,"h":22},
	"sourceSize": {"w":32,"h":22}
},
{
	"filename": "mc.png",
	"frame": {"x":91,"y":211,"w":32,"h":22},
	"rotated": true,
	"trimmed": false,
	"spriteSourceSize": {"x":0,"y":0,"w":32,"h":22},
	"sourceSize": {"w":32,"h":22}
},
{
	"filename": "md.png",
	"frame": {"x":415,"y":199,"w":32,"h":22},
	"rotated": false,
	"trimmed": false,
	"spriteSourceSize": {"x":0,"y":0,"w":32,"h":22},
	"sourceSize": {"w":32,"h":22}
},
{
	"filename": "me.png",
	"frame": {"x":3,"y":3,"w":32,"h":24},
	"rotated": false,
	"trimmed": false,
	"spriteSourceSize": {"x":0,"y":0,"w":32,"h":24},
	"sourceSize": {"w":32,"h":24}
},
{
	"filename": "mg.png",
	"frame": {"x":379,"y":185,"w":32,"h":22},
	"rotated": false,
	"trimmed": false,
	"spriteSourceSize": {"x":0,"y":0,"w":32,"h":22},
	"sourceSize": {"w":32,"h":22}
},
{
	"filename": "mh.png",
	"frame": {"x":343,"y":185,"w":32,"h":22},
	"rotated": false,
	"trimmed": false,
	"spriteSourceSize": {"x":0,"y":0,"w":32,"h":22},
	"sourceSize": {"w":32,"h":22}
},
{
	"filename": "mk.png",
	"frame": {"x":307,"y":185,"w":32,"h":22},
	"rotated": false,
	"trimmed": false,
	"spriteSourceSize": {"x":0,"y":0,"w":32,"h":22},
	"sourceSize": {"w":32,"h":22}
},
{
	"filename": "ml.png",
	"frame": {"x":271,"y":185,"w":32,"h":22},
	"rotated": false,
	"trimmed": false,
	"spriteSourceSize": {"x":0,"y":0,"w":32,"h":22},
	"sourceSize": {"w":32,"h":22}
},
{
	"filename": "mm.png",
	"frame": {"x":235,"y":185,"w":32,"h":22},
	"rotated": false,
	"trimmed": false,
	"spriteSourceSize": {"x":0,"y":0,"w":32,"h":22},
	"sourceSize": {"w":32,"h":22}
},
{
	"filename": "mn.png",
	"frame": {"x":199,"y":185,"w":32,"h":22},
	"rotated": false,
	"trimmed": false,
	"spriteSourceSize": {"x":0,"y":0,"w":32,"h":22},
	"sourceSize": {"w":32,"h":22}
},
{
	"filename": "mo.png",
	"frame": {"x":163,"y":185,"w":32,"h":22},
	"rotated": false,
	"trimmed": false,
	"spriteSourceSize": {"x":0,"y":0,"w":32,"h":22},
	"sourceSize": {"w":32,"h":22}
},
{
	"filename": "mp.png",
	"frame": {"x":127,"y":185,"w":32,"h":22},
	"rotated": false,
	"trimmed": false,
	"spriteSourceSize": {"x":0,"y":0,"w":32,"h":22},
	"sourceSize": {"w":32,"h":22}
},
{
	"filename": "mq.png",
	"frame": {"x":3,"y":239,"w":32,"h":22},
	"rotated": false,
	"trimmed": false,
	"spriteSourceSize": {"x":0,"y":0,"w":32,"h":22},
	"sourceSize": {"w":32,"h":22}
},
{
	"filename": "mr.png",
	"frame": {"x":3,"y":213,"w":32,"h":22},
	"rotated": false,
	"trimmed": false,
	"spriteSourceSize": {"x":0,"y":0,"w":32,"h":22},
	"sourceSize": {"w":32,"h":22}
},
{
	"filename": "ms.png",
	"frame": {"x":39,"y":205,"w":32,"h":22},
	"rotated": true,
	"trimmed": false,
	"spriteSourceSize": {"x":0,"y":0,"w":32,"h":22},
	"sourceSize": {"w":32,"h":22}
},
{
	"filename": "mt.png",
	"frame": {"x":65,"y":195,"w":32,"h":22},
	"rotated": true,
	"trimmed": false,
	"spriteSourceSize": {"x":0,"y":0,"w":32,"h":22},
	"sourceSize": {"w":32,"h":22}
},
{
	"filename": "mu.png",
	"frame": {"x":91,"y":185,"w":32,"h":22},
	"rotated": false,
	"trimmed": false,
	"spriteSourceSize": {"x":0,"y":0,"w":32,"h":22},
	"sourceSize": {"w":32,"h":22}
},
{
	"filename": "mv.png",
	"frame": {"x":415,"y":173,"w":32,"h":22},
	"rotated": false,
	"trimmed": false,
	"spriteSourceSize": {"x":0,"y":0,"w":32,"h":22},
	"sourceSize": {"w":32,"h":22}
},
{
	"filename": "mw.png",
	"frame": {"x":379,"y":159,"w":32,"h":22},
	"rotated": false,
	"trimmed": false,
	"spriteSourceSize": {"x":0,"y":0,"w":32,"h":22},
	"sourceSize": {"w":32,"h":22}
},
{
	"filename": "mx.png",
	"frame": {"x":343,"y":159,"w":32,"h":22},
	"rotated": false,
	"trimmed": false,
	"spriteSourceSize": {"x":0,"y":0,"w":32,"h":22},
	"sourceSize": {"w":32,"h":22}
},
{
	"filename": "my.png",
	"frame": {"x":307,"y":159,"w":32,"h":22},
	"rotated": false,
	"trimmed": false,
	"spriteSourceSize": {"x":0,"y":0,"w":32,"h":22},
	"sourceSize": {"w":32,"h":22}
},
{
	"filename": "mz.png",
	"frame": {"x":271,"y":159,"w":32,"h":22},
	"rotated": false,
	"trimmed": false,
	"spriteSourceSize": {"x":0,"y":0,"w":32,"h":22},
	"sourceSize": {"w":32,"h":22}
},
{
	"filename": "na.png",
	"frame": {"x":235,"y":159,"w":32,"h":22},
	"rotated": false,
	"trimmed": false,
	"spriteSourceSize": {"x":0,"y":0,"w":32,"h":22},
	"sourceSize": {"w":32,"h":22}
},
{
	"filename": "nc.png",
	"frame": {"x":199,"y":159,"w":32,"h":22},
	"rotated": false,
	"trimmed": false,
	"spriteSourceSize": {"x":0,"y":0,"w":32,"h":22},
	"sourceSize": {"w":32,"h":22}
},
{
	"filename": "ne.png",
	"frame": {"x":163,"y":159,"w":32,"h":22},
	"rotated": false,
	"trimmed": false,
	"spriteSourceSize": {"x":0,"y":0,"w":32,"h":22},
	"sourceSize": {"w":32,"h":22}
},
{
	"filename": "nf.png",
	"frame": {"x":127,"y":159,"w":32,"h":22},
	"rotated": false,
	"trimmed": false,
	"spriteSourceSize": {"x":0,"y":0,"w":32,"h":22},
	"sourceSize": {"w":32,"h":22}
},
{
	"filename": "ng.png",
	"frame": {"x":91,"y":159,"w":32,"h":22},
	"rotated": false,
	"trimmed": false,
	"spriteSourceSize": {"x":0,"y":0,"w":32,"h":22},
	"sourceSize": {"w":32,"h":22}
},
{
	"filename": "ni.png",
	"frame": {"x":3,"y":187,"w":32,"h":22},
	"rotated": false,
	"trimmed": false,
	"spriteSourceSize": {"x":0,"y":0,"w":32,"h":22},
	"sourceSize": {"w":32,"h":22}
},
{
	"filename": "nl.png",
	"frame": {"x":39,"y":169,"w":32,"h":22},
	"rotated": true,
	"trimmed": false,
	"spriteSourceSize": {"x":0,"y":0,"w":32,"h":22},
	"sourceSize": {"w":32,"h":22}
},
{
	"filename": "no.png",
	"frame": {"x":247,"y":341,"w":32,"h":22},
	"rotated": true,
	"trimmed": false,
	"spriteSourceSize": {"x":0,"y":0,"w":32,"h":22},
	"sourceSize": {"w":32,"h":22}
},
{
	"filename": "np.png",
	"frame": {"x":143,"y":489,"w":18,"h":22},
	"rotated": true,
	"trimmed": false,
	"spriteSourceSize": {"x":0,"y":0,"w":18,"h":22},
	"sourceSize": {"w":18,"h":22}
},
{
	"filename": "nr.png",
	"frame": {"x":65,"y":159,"w":32,"h":22},
	"rotated": true,
	"trimmed": false,
	"spriteSourceSize": {"x":0,"y":0,"w":32,"h":22},
	"sourceSize": {"w":32,"h":22}
},
{
	"filename": "nu.png",
	"frame": {"x":425,"y":147,"w":32,"h":22},
	"rotated": false,
	"trimmed": false,
	"spriteSourceSize": {"x":0,"y":0,"w":32,"h":22},
	"sourceSize": {"w":32,"h":22}
},
{
	"filename": "nz.png",
	"frame": {"x":389,"y":133,"w":32,"h":22},
	"rotated": false,
	"trimmed": false,
	"spriteSourceSize": {"x":0,"y":0,"w":32,"h":22},
	"sourceSize": {"w":32,"h":22}
},
{
	"filename": "om.png",
	"frame": {"x":353,"y":133,"w":32,"h":22},
	"rotated": false,
	"trimmed": false,
	"spriteSourceSize": {"x":0,"y":0,"w":32,"h":22},
	"sourceSize": {"w":32,"h":22}
},
{
	"filename": "pa.png",
	"frame": {"x":317,"y":133,"w":32,"h":22},
	"rotated": false,
	"trimmed": false,
	"spriteSourceSize": {"x":0,"y":0,"w":32,"h":22},
	"sourceSize": {"w":32,"h":22}
},
{
	"filename": "pe.png",
	"frame": {"x":281,"y":133,"w":32,"h":22},
	"rotated": false,
	"trimmed": false,
	"spriteSourceSize": {"x":0,"y":0,"w":32,"h":22},
	"sourceSize": {"w":32,"h":22}
},
{
	"filename": "pf.png",
	"frame": {"x":245,"y":133,"w":32,"h":22},
	"rotated": false,
	"trimmed": false,
	"spriteSourceSize": {"x":0,"y":0,"w":32,"h":22},
	"sourceSize": {"w":32,"h":22}
},
{
	"filename": "pg.png",
	"frame": {"x":209,"y":133,"w":32,"h":22},
	"rotated": false,
	"trimmed": false,
	"spriteSourceSize": {"x":0,"y":0,"w":32,"h":22},
	"sourceSize": {"w":32,"h":22}
},
{
	"filename": "ph.png",
	"frame": {"x":173,"y":133,"w":32,"h":22},
	"rotated": false,
	"trimmed": false,
	"spriteSourceSize": {"x":0,"y":0,"w":32,"h":22},
	"sourceSize": {"w":32,"h":22}
},
{
	"filename": "pk.png",
	"frame": {"x":137,"y":133,"w":32,"h":22},
	"rotated": false,
	"trimmed": false,
	"spriteSourceSize": {"x":0,"y":0,"w":32,"h":22},
	"sourceSize": {"w":32,"h":22}
},
{
	"filename": "pl.png",
	"frame": {"x":101,"y":133,"w":32,"h":22},
	"rotated": false,
	"trimmed": false,
	"spriteSourceSize": {"x":0,"y":0,"w":32,"h":22},
	"sourceSize": {"w":32,"h":22}
},
{
	"filename": "pm.png",
	"frame": {"x":65,"y":133,"w":32,"h":22},
	"rotated": false,
	"trimmed": false,
	"spriteSourceSize": {"x":0,"y":0,"w":32,"h":22},
	"sourceSize": {"w":32,"h":22}
},
{
	"filename": "pn.png",
	"frame": {"x":3,"y":161,"w":32,"h":22},
	"rotated": false,
	"trimmed": false,
	"spriteSourceSize": {"x":0,"y":0,"w":32,"h":22},
	"sourceSize": {"w":32,"h":22}
},
{
	"filename": "pr.png",
	"frame": {"x":3,"y":135,"w":32,"h":22},
	"rotated": false,
	"trimmed": false,
	"spriteSourceSize": {"x":0,"y":0,"w":32,"h":22},
	"sourceSize": {"w":32,"h":22}
},
{
	"filename": "ps.png",
	"frame": {"x":39,"y":133,"w":32,"h":22},
	"rotated": true,
	"trimmed": false,
	"spriteSourceSize": {"x":0,"y":0,"w":32,"h":22},
	"sourceSize": {"w":32,"h":22}
},
{
	"filename": "pt.png",
	"frame": {"x":435,"y":111,"w":32,"h":22},
	"rotated": true,
	"trimmed": false,
	"spriteSourceSize": {"x":0,"y":0,"w":32,"h":22},
	"sourceSize": {"w":32,"h":22}
},
{
	"filename": "pw.png",
	"frame": {"x":399,"y":107,"w":32,"h":22},
	"rotated": false,
	"trimmed": false,
	"spriteSourceSize": {"x":0,"y":0,"w":32,"h":22},
	"sourceSize": {"w":32,"h":22}
},
{
	"filename": "py.png",
	"frame": {"x":363,"y":107,"w":32,"h":22},
	"rotated": false,
	"trimmed": false,
	"spriteSourceSize": {"x":0,"y":0,"w":32,"h":22},
	"sourceSize": {"w":32,"h":22}
},
{
	"filename": "qa.png",
	"frame": {"x":327,"y":107,"w":32,"h":22},
	"rotated": false,
	"trimmed": false,
	"spriteSourceSize": {"x":0,"y":0,"w":32,"h":22},
	"sourceSize": {"w":32,"h":22}
},
{
	"filename": "re.png",
	"frame": {"x":117,"y":345,"w":32,"h":22},
	"rotated": true,
	"trimmed": false,
	"spriteSourceSize": {"x":0,"y":0,"w":32,"h":22},
	"sourceSize": {"w":32,"h":22}
},
{
	"filename": "ro.png",
	"frame": {"x":291,"y":107,"w":32,"h":22},
	"rotated": false,
	"trimmed": false,
	"spriteSourceSize": {"x":0,"y":0,"w":32,"h":22},
	"sourceSize": {"w":32,"h":22}
},
{
	"filename": "rs.png",
	"frame": {"x":255,"y":107,"w":32,"h":22},
	"rotated": false,
	"trimmed": false,
	"spriteSourceSize": {"x":0,"y":0,"w":32,"h":22},
	"sourceSize": {"w":32,"h":22}
},
{
	"filename": "ru.png",
	"frame": {"x":219,"y":107,"w":32,"h":22},
	"rotated": false,
	"trimmed": false,
	"spriteSourceSize": {"x":0,"y":0,"w":32,"h":22},
	"sourceSize": {"w":32,"h":22}
},
{
	"filename": "rw.png",
	"frame": {"x":183,"y":107,"w":32,"h":22},
	"rotated": false,
	"trimmed": false,
	"spriteSourceSize": {"x":0,"y":0,"w":32,"h":22},
	"sourceSize": {"w":32,"h":22}
},
{
	"filename": "sa.png",
	"frame": {"x":147,"y":107,"w":32,"h":22},
	"rotated": false,
	"trimmed": false,
	"spriteSourceSize": {"x":0,"y":0,"w":32,"h":22},
	"sourceSize": {"w":32,"h":22}
},
{
	"filename": "sb.png",
	"frame": {"x":111,"y":107,"w":32,"h":22},
	"rotated": false,
	"trimmed": false,
	"spriteSourceSize": {"x":0,"y":0,"w":32,"h":22},
	"sourceSize": {"w":32,"h":22}
},
{
	"filename": "sc.png",
	"frame": {"x":75,"y":107,"w":32,"h":22},
	"rotated": false,
	"trimmed": false,
	"spriteSourceSize": {"x":0,"y":0,"w":32,"h":22},
	"sourceSize": {"w":32,"h":22}
},
{
	"filename": "sd.png",
	"frame": {"x":3,"y":109,"w":32,"h":22},
	"rotated": false,
	"trimmed": false,
	"spriteSourceSize": {"x":0,"y":0,"w":32,"h":22},
	"sourceSize": {"w":32,"h":22}
},
{
	"filename": "se.png",
	"frame": {"x":39,"y":107,"w":32,"h":22},
	"rotated": false,
	"trimmed": false,
	"spriteSourceSize": {"x":0,"y":0,"w":32,"h":22},
	"sourceSize": {"w":32,"h":22}
},
{
	"filename": "sg.png",
	"frame": {"x":399,"y":81,"w":32,"h":22},
	"rotated": false,
	"trimmed": false,
	"spriteSourceSize": {"x":0,"y":0,"w":32,"h":22},
	"sourceSize": {"w":32,"h":22}
},
{
	"filename": "sh.png",
	"frame": {"x":363,"y":81,"w":32,"h":22},
	"rotated": false,
	"trimmed": false,
	"spriteSourceSize": {"x":0,"y":0,"w":32,"h":22},
	"sourceSize": {"w":32,"h":22}
},
{
	"filename": "si.png",
	"frame": {"x":327,"y":81,"w":32,"h":22},
	"rotated": false,
	"trimmed": false,
	"spriteSourceSize": {"x":0,"y":0,"w":32,"h":22},
	"sourceSize": {"w":32,"h":22}
},
{
	"filename": "sj.png",
	"frame": {"x":247,"y":341,"w":32,"h":22},
	"rotated": true,
	"trimmed": false,
	"spriteSourceSize": {"x":0,"y":0,"w":32,"h":22},
	"sourceSize": {"w":32,"h":22}
},
{
	"filename": "sk.png",
	"frame": {"x":291,"y":81,"w":32,"h":22},
	"rotated": false,
	"trimmed": false,
	"spriteSourceSize": {"x":0,"y":0,"w":32,"h":22},
	"sourceSize": {"w":32,"h":22}
},
{
	"filename": "sl.png",
	"frame": {"x":255,"y":81,"w":32,"h":22},
	"rotated": false,
	"trimmed": false,
	"spriteSourceSize": {"x":0,"y":0,"w":32,"h":22},
	"sourceSize": {"w":32,"h":22}
},
{
	"filename": "sm.png",
	"frame": {"x":219,"y":81,"w":32,"h":22},
	"rotated": false,
	"trimmed": false,
	"spriteSourceSize": {"x":0,"y":0,"w":32,"h":22},
	"sourceSize": {"w":32,"h":22}
},
{
	"filename": "sn.png",
	"frame": {"x":183,"y":81,"w":32,"h":22},
	"rotated": false,
	"trimmed": false,
	"spriteSourceSize": {"x":0,"y":0,"w":32,"h":22},
	"sourceSize": {"w":32,"h":22}
},
{
	"filename": "so.png",
	"frame": {"x":147,"y":81,"w":32,"h":22},
	"rotated": false,
	"trimmed": false,
	"spriteSourceSize": {"x":0,"y":0,"w":32,"h":22},
	"sourceSize": {"w":32,"h":22}
},
{
	"filename": "sr.png",
	"frame": {"x":111,"y":81,"w":32,"h":22},
	"rotated": false,
	"trimmed": false,
	"spriteSourceSize": {"x":0,"y":0,"w":32,"h":22},
	"sourceSize": {"w":32,"h":22}
},
{
	"filename": "ss.png",
	"frame": {"x":75,"y":81,"w":32,"h":22},
	"rotated": false,
	"trimmed": false,
	"spriteSourceSize": {"x":0,"y":0,"w":32,"h":22},
	"sourceSize": {"w":32,"h":22}
},
{
	"filename": "st.png",
	"frame": {"x":3,"y":83,"w":32,"h":22},
	"rotated": false,
	"trimmed": false,
	"spriteSourceSize": {"x":0,"y":0,"w":32,"h":22},
	"sourceSize": {"w":32,"h":22}
},
{
	"filename": "sv.png",
	"frame": {"x":39,"y":81,"w":32,"h":22},
	"rotated": false,
	"trimmed": false,
	"spriteSourceSize": {"x":0,"y":0,"w":32,"h":22},
	"sourceSize": {"w":32,"h":22}
},
{
	"filename": "sy.png",
	"frame": {"x":435,"y":75,"w":32,"h":22},
	"rotated": true,
	"trimmed": false,
	"spriteSourceSize": {"x":0,"y":0,"w":32,"h":22},
	"sourceSize": {"w":32,"h":22}
},
{
	"filename": "sz.png",
	"frame": {"x":399,"y":55,"w":32,"h":22},
	"rotated": false,
	"trimmed": false,
	"spriteSourceSize": {"x":0,"y":0,"w":32,"h":22},
	"sourceSize": {"w":32,"h":22}
},
{
	"filename": "tc.png",
	"frame": {"x":363,"y":55,"w":32,"h":22},
	"rotated": false,
	"trimmed": false,
	"spriteSourceSize": {"x":0,"y":0,"w":32,"h":22},
	"sourceSize": {"w":32,"h":22}
},
{
	"filename": "td.png",
	"frame": {"x":327,"y":55,"w":32,"h":22},
	"rotated": false,
	"trimmed": false,
	"spriteSourceSize": {"x":0,"y":0,"w":32,"h":22},
	"sourceSize": {"w":32,"h":22}
},
{
	"filename": "tf.png",
	"frame": {"x":291,"y":55,"w":32,"h":22},
	"rotated": false,
	"trimmed": false,
	"spriteSourceSize": {"x":0,"y":0,"w":32,"h":22},
	"sourceSize": {"w":32,"h":22}
},
{
	"filename": "tg.png",
	"frame": {"x":255,"y":55,"w":32,"h":22},
	"rotated": false,
	"trimmed": false,
	"spriteSourceSize": {"x":0,"y":0,"w":32,"h":22},
	"sourceSize": {"w":32,"h":22}
},
{
	"filename": "th.png",
	"frame": {"x":219,"y":55,"w":32,"h":22},
	"rotated": false,
	"trimmed": false,
	"spriteSourceSize": {"x":0,"y":0,"w":32,"h":22},
	"sourceSize": {"w":32,"h":22}
},
{
	"filename": "tj.png",
	"frame": {"x":183,"y":55,"w":32,"h":22},
	"rotated": false,
	"trimmed": false,
	"spriteSourceSize": {"x":0,"y":0,"w":32,"h":22},
	"sourceSize": {"w":32,"h":22}
},
{
	"filename": "tk.png",
	"frame": {"x":147,"y":55,"w":32,"h":22},
	"rotated": false,
	"trimmed": false,
	"spriteSourceSize": {"x":0,"y":0,"w":32,"h":22},
	"sourceSize": {"w":32,"h":22}
},
{
	"filename": "tl.png",
	"frame": {"x":111,"y":55,"w":32,"h":22},
	"rotated": false,
	"trimmed": false,
	"spriteSourceSize": {"x":0,"y":0,"w":32,"h":22},
	"sourceSize": {"w":32,"h":22}
},
{
	"filename": "tm.png",
	"frame": {"x":75,"y":55,"w":32,"h":22},
	"rotated": false,
	"trimmed": false,
	"spriteSourceSize": {"x":0,"y":0,"w":32,"h":22},
	"sourceSize": {"w":32,"h":22}
},
{
	"filename": "tn.png",
	"frame": {"x":3,"y":57,"w":32,"h":22},
	"rotated": false,
	"trimmed": false,
	"spriteSourceSize": {"x":0,"y":0,"w":32,"h":22},
	"sourceSize": {"w":32,"h":22}
},
{
	"filename": "to.png",
	"frame": {"x":39,"y":55,"w":32,"h":22},
	"rotated": false,
	"trimmed": false,
	"spriteSourceSize": {"x":0,"y":0,"w":32,"h":22},
	"sourceSize": {"w":32,"h":22}
},
{
	"filename": "tr.png",
	"frame": {"x":435,"y":39,"w":32,"h":22},
	"rotated": true,
	"trimmed": false,
	"spriteSourceSize": {"x":0,"y":0,"w":32,"h":22},
	"sourceSize": {"w":32,"h":22}
},
{
	"filename": "tt.png",
	"frame": {"x":399,"y":29,"w":32,"h":22},
	"rotated": false,
	"trimmed": false,
	"spriteSourceSize": {"x":0,"y":0,"w":32,"h":22},
	"sourceSize": {"w":32,"h":22}
},
{
	"filename": "tv.png",
	"frame": {"x":363,"y":29,"w":32,"h":22},
	"rotated": false,
	"trimmed": false,
	"spriteSourceSize": {"x":0,"y":0,"w":32,"h":22},
	"sourceSize": {"w":32,"h":22}
},
{
	"filename": "tw.png",
	"frame": {"x":327,"y":29,"w":32,"h":22},
	"rotated": false,
	"trimmed": false,
	"spriteSourceSize": {"x":0,"y":0,"w":32,"h":22},
	"sourceSize": {"w":32,"h":22}
},
{
	"filename": "tz.png",
	"frame": {"x":291,"y":29,"w":32,"h":22},
	"rotated": false,
	"trimmed": false,
	"spriteSourceSize": {"x":0,"y":0,"w":32,"h":22},
	"sourceSize": {"w":32,"h":22}
},
{
	"filename": "ua.png",
	"frame": {"x":255,"y":29,"w":32,"h":22},
	"rotated": false,
	"trimmed": false,
	"spriteSourceSize": {"x":0,"y":0,"w":32,"h":22},
	"sourceSize": {"w":32,"h":22}
},
{
	"filename": "ug.png",
	"frame": {"x":219,"y":29,"w":32,"h":22},
	"rotated": false,
	"trimmed": false,
	"spriteSourceSize": {"x":0,"y":0,"w":32,"h":22},
	"sourceSize": {"w":32,"h":22}
},
{
	"filename": "um.png",
	"frame": {"x":183,"y":29,"w":32,"h":22},
	"rotated": false,
	"trimmed": false,
	"spriteSourceSize": {"x":0,"y":0,"w":32,"h":22},
	"sourceSize": {"w":32,"h":22}
},
{
	"filename": "us.png",
	"frame": {"x":147,"y":29,"w":32,"h":22},
	"rotated": false,
	"trimmed": false,
	"spriteSourceSize": {"x":0,"y":0,"w":32,"h":22},
	"sourceSize": {"w":32,"h":22}
},
{
	"filename": "uy.png",
	"frame": {"x":111,"y":29,"w":32,"h":22},
	"rotated": false,
	"trimmed": false,
	"spriteSourceSize": {"x":0,"y":0,"w":32,"h":22},
	"sourceSize": {"w":32,"h":22}
},
{
	"filename": "uz.png",
	"frame": {"x":75,"y":29,"w":32,"h":22},
	"rotated": false,
	"trimmed": false,
	"spriteSourceSize": {"x":0,"y":0,"w":32,"h":22},
	"sourceSize": {"w":32,"h":22}
},
{
	"filename": "va.png",
	"frame": {"x":3,"y":31,"w":32,"h":22},
	"rotated": false,
	"trimmed": false,
	"spriteSourceSize": {"x":0,"y":0,"w":32,"h":22},
	"sourceSize": {"w":32,"h":22}
},
{
	"filename": "vc.png",
	"frame": {"x":39,"y":29,"w":32,"h":22},
	"rotated": false,
	"trimmed": false,
	"spriteSourceSize": {"x":0,"y":0,"w":32,"h":22},
	"sourceSize": {"w":32,"h":22}
},
{
	"filename": "ve.png",
	"frame": {"x":435,"y":3,"w":32,"h":22},
	"rotated": true,
	"trimmed": false,
	"spriteSourceSize": {"x":0,"y":0,"w":32,"h":22},
	"sourceSize": {"w":32,"h":22}
},
{
	"filename": "vg.png",
	"frame": {"x":399,"y":3,"w":32,"h":22},
	"rotated": false,
	"trimmed": false,
	"spriteSourceSize": {"x":0,"y":0,"w":32,"h":22},
	"sourceSize": {"w":32,"h":22}
},
{
	"filename": "vi.png",
	"frame": {"x":363,"y":3,"w":32,"h":22},
	"rotated": false,
	"trimmed": false,
	"spriteSourceSize": {"x":0,"y":0,"w":32,"h":22},
	"sourceSize": {"w":32,"h":22}
},
{
	"filename": "vn.png",
	"frame": {"x":327,"y":3,"w":32,"h":22},
	"rotated": false,
	"trimmed": false,
	"spriteSourceSize": {"x":0,"y":0,"w":32,"h":22},
	"sourceSize": {"w":32,"h":22}
},
{
	"filename": "vu.png",
	"frame": {"x":291,"y":3,"w":32,"h":22},
	"rotated": false,
	"trimmed": false,
	"spriteSourceSize": {"x":0,"y":0,"w":32,"h":22},
	"sourceSize": {"w":32,"h":22}
},
{
	"filename": "wf.png",
	"frame": {"x":255,"y":3,"w":32,"h":22},
	"rotated": false,
	"trimmed": false,
	"spriteSourceSize": {"x":0,"y":0,"w":32,"h":22},
	"sourceSize": {"w":32,"h":22}
},
{
	"filename": "ws.png",
	"frame": {"x":219,"y":3,"w":32,"h":22},
	"rotated": false,
	"trimmed": false,
	"spriteSourceSize": {"x":0,"y":0,"w":32,"h":22},
	"sourceSize": {"w":32,"h":22}
},
{
	"filename": "ye.png",
	"frame": {"x":183,"y":3,"w":32,"h":22},
	"rotated": false,
	"trimmed": false,
	"spriteSourceSize": {"x":0,"y":0,"w":32,"h":22},
	"sourceSize": {"w":32,"h":22}
},
{
	"filename": "yt.png",
	"frame": {"x":147,"y":3,"w":32,"h":22},
	"rotated": false,
	"trimmed": false,
	"spriteSourceSize": {"x":0,"y":0,"w":32,"h":22},
	"sourceSize": {"w":32,"h":22}
},
{
	"filename": "za.png",
	"frame": {"x":111,"y":3,"w":32,"h":22},
	"rotated": false,
	"trimmed": false,
	"spriteSourceSize": {"x":0,"y":0,"w":32,"h":22},
	"sourceSize": {"w":32,"h":22}
},
{
	"filename": "zm.png",
	"frame": {"x":75,"y":3,"w":32,"h":22},
	"rotated": false,
	"trimmed": false,
	"spriteSourceSize": {"x":0,"y":0,"w":32,"h":22},
	"sourceSize": {"w":32,"h":22}
},
{
	"filename": "zw.png",
	"frame": {"x":39,"y":3,"w":32,"h":22},
	"rotated": false,
	"trimmed": false,
	"spriteSourceSize": {"x":0,"y":0,"w":32,"h":22},
	"sourceSize": {"w":32,"h":22}
}],
"meta": {
	"app": "http://www.codeandweb.com/texturepacker ",
	"version": "1.0",
	"image": "flags@2.png",
	"format": "RGBA8888",
	"size": {"w":460,"h":512},
	"scale": "1",
	"smartupdate": "$TexturePacker:SmartUpdate:3dde0cd59cb40a9f325f3004beaf8114:58d53a60c5ebe96460b851fde92ac925:3b7fd62f1a6db5d804a0df609601563c$"
}
}
